beauty
test
